metno/__init__.py
PyMetno-0.13.0.dist-info/LICENSE
PyMetno-0.13.0.dist-info/METADATA
PyMetno-0.13.0.dist-info/WHEEL
PyMetno-0.13.0.dist-info/top_level.txt
PyMetno-0.13.0.dist-info/RECORD
