Metadata-Version: 2.1
Name: PyMetno
Version: 0.13.0
Summary: A library to communicate with the met.no api
Home-page: https://github.com/Danielhiversen/pyMetno/
Author: Daniel Hjelseth Høyer
License: MIT
Classifier: Development Status :: 3 - Alpha
Classifier: Environment :: Other Environment
Classifier: Intended Audience :: Developers
Classifier: Operating System :: OS Independent
Classifier: Programming Language :: Python
Classifier: Topic :: Home Automation
Classifier: Topic :: Software Development :: Libraries :: Python Modules
License-File: LICENSE
Requires-Dist: xmltodict
Requires-Dist: aiohttp>=3.0.6
Requires-Dist: async_timeout>=3.0.0
